nnlocallinear/__init__.py
nnlocallinear/core.py
nnlocallinear/lmethods.py
nnlocallinear/predict.py
nnlocallinear-0.0.5.dist-info/LICENSE
nnlocallinear-0.0.5.dist-info/METADATA
nnlocallinear-0.0.5.dist-info/WHEEL
nnlocallinear-0.0.5.dist-info/top_level.txt
nnlocallinear-0.0.5.dist-info/RECORD
