Metadata-Version: 2.1
Name: nnlocallinear
Version: 0.0.5
Summary: Conformal prediction using neural networks
Home-page: UNKNOWN
Author: Marco Inacio, Victor Coscrato
Author-email: pythonpackages@marcoinacio.com
License: GPL3
Keywords: neural networks,local linear regression
Platform: UNKNOWN
Requires-Dist: numpy
Requires-Dist: scikit-learn
Requires-Dist: torch
